MANIFEST.in
requirements.txt
setup.py
serial_button_manager/__init__.py
serial_button_manager/cmdline.py
serial_button_manager/manager.py
serial_button_manager.egg-info/PKG-INFO
serial_button_manager.egg-info/SOURCES.txt
serial_button_manager.egg-info/dependency_links.txt
serial_button_manager.egg-info/entry_points.txt
serial_button_manager.egg-info/requires.txt
serial_button_manager.egg-info/top_level.txt