Metadata-Version: 1.1
Name: serial-button-manager
Version: 0.1.4
Summary: Control whether or not a service is running with an easy-to-construct button connected to a serial port.
Home-page: http://github.com/coddingtonbear/serial-button-manager
Author: Adam Coddington
Author-email: me@adamcoddington.net
License: UNKNOWN
Platform: UNKNOWN
Classifier: Development Status :: 4 - Beta
Classifier: Intended Audience :: Developers
Classifier: License :: OSI Approved :: MIT License
Classifier: Operating System :: MacOS :: MacOS X
Classifier: Operating System :: Microsoft :: Windows
Classifier: Operating System :: POSIX
